gatohep/__init__.py
gatohep/data_generation.py
gatohep/losses.py
gatohep/models.py
gatohep/plotting_utils.py
gatohep/utils.py
gato_hep-0.2.1.dist-info/LICENSE
gato_hep-0.2.1.dist-info/METADATA
gato_hep-0.2.1.dist-info/WHEEL
gato_hep-0.2.1.dist-info/top_level.txt
gato_hep-0.2.1.dist-info/RECORD
