Metadata-Version: 2.1
Name: gato-hep
Version: 0.2.1
Summary: GATO: Gradient-based cATegorization Optimizer for High-Energy Physics
Author-email: Florian Mausolf <florian.mausolf@rwth-aachen.de>
License: MIT License
Project-URL: Homepage, https://github.com/FloMau/gato-hep
Project-URL: Repository, https://github.com/FloMau/gato-hep
Project-URL: Documentation, https://gato-hep.readthedocs.io/en/latest/
Project-URL: Issues, https://github.com/FloMau/gato-hep/issues
Keywords: differentiable,binning,optimization,HEP,significance
Classifier: Development Status :: 3 - Alpha
Classifier: Intended Audience :: Science/Research
Classifier: License :: OSI Approved :: MIT License
Classifier: Operating System :: OS Independent
Classifier: Programming Language :: Python
Classifier: Programming Language :: Python :: 3
Classifier: Programming Language :: Python :: 3.10
Classifier: Programming Language :: Python :: 3.11
Classifier: Programming Language :: Python :: 3.12
Classifier: Topic :: Scientific/Engineering :: Physics
Requires-Python: >=3.10
License-File: LICENSE
Requires-Dist: numpy >=1.26
Requires-Dist: tf-keras ==2.19.0
Requires-Dist: ml-dtypes >=0.4.1
Requires-Dist: mplhep
Requires-Dist: matplotlib >=3.7
Requires-Dist: pillow >=10.0
Requires-Dist: scipy
Requires-Dist: pandas
Requires-Dist: hist
Requires-Dist: tensorflow <2.20,>=2.17 ; extra != "gpu"
Requires-Dist: tensorflow-probability >=0.24 ; extra != "gpu"
Provides-Extra: cpu
Requires-Dist: tensorflow <2.20,>=2.17 ; extra == 'cpu'
Requires-Dist: tensorflow-probability >=0.24 ; extra == 'cpu'
Provides-Extra: dev
Requires-Dist: pytest ; extra == 'dev'
Requires-Dist: pytest-cov ; extra == 'dev'
Requires-Dist: flake8 ; extra == 'dev'
Provides-Extra: docs
Requires-Dist: sphinx >=5.0 ; extra == 'docs'
Requires-Dist: sphinx-rtd-theme ; extra == 'docs'
Requires-Dist: sphinx-autodoc-typehints ; extra == 'docs'
Requires-Dist: sphinx-autoapi ; extra == 'docs'
Requires-Dist: myst-parser ; extra == 'docs'
Requires-Dist: pydata-sphinx-theme ; extra == 'docs'
Provides-Extra: gpu
Requires-Dist: tensorflow[and-cuda] <2.20,>=2.17 ; extra == 'gpu'
Requires-Dist: tensorflow-probability >=0.24 ; extra == 'gpu'
